{"Sector": "Consumer Cyclical", "Industry": "Gambling", "Country": "USA", "Index": "", "PE": "12.15", "EPSttm": "0.73", "InsiderOwn": "5.70", "ShsOutstand": 89990000.0, "PerfWeek": "6.73", "LastUpdated": "2023-01-13", "MarketCap": 758440000.0, "ForwardPE": "10.06", "EPSnextY": "2.20", "InsiderTrans": "-1.97", "ShsFloat": 53600000.0, "PerfMonth": "7.64", "Income": 67500000.0, "PEG": "2.80", "EPSnextQ": "0.23", "InstOwn": "67.80", "ShortFloatRatio": "3.32 / 7.64", "PerfQuarter": "5.46", "Sales": 884000000.0, "PS": "0.86", "EPSthisY": "14.70", "InstTrans": "-2.78", "ShortInterest": 1780000.0, "PerfHalfY": "-18.76", "Booksh": "2.01", "PB": "4.42", "ROA": "9.30", "TargetPrice": "13.00", "PerfYear": "-31.16", "Cashsh": "2.86", "PC": "3.11", "EPSnext5Y": "4.34", "ROE": "39.70", "FiftyTwoWRange": [7.26, 14.04], "PerfYTD": "15.32", "Dividend": "", "PFCF": "11.72", "EPSpast5Y": "", "ROI": "10.80", "FiftyTwoWHigh": "-36.75", "Beta": "1.19", "DividendPercent": "", "QuickRatio": "3.00", "Salespast5Y": "", "GrossMargin": "31.50", "FiftyTwoWLow": "22.31", "ATR": "0.27", "Employees": "900", "CurrentRatio": "3.10", "SalesQQ": "38.10", "OperMargin": "9.90", "RSI14": "66.24", "Volatility": [2.78, 3.14], "Optionable": true, "DebtEq": "2.88", "EPSQQ": "117.30", "ProfitMargin": "7.60", "RelVolume": "0.42", "PrevClose": "8.88", "Shortable": true, "LTDebtEq": "2.75", "Earnings": "Nov 08 AMC", "Payout": "0.00", "AvgVolume": 232810.0, "Price": "8.88", "Recom": "2.00", "SMA20": "11.56", "SMA50": "4.73", "SMA200": "-10.78", "Volume": "31987", "Change": "0.00"}