{"Sector": "Healthcare", "Industry": "Biotechnology", "Country": "Canada", "Exchange": "NASD", "Index": "", "PE": "", "EPSttm": "-1.29", "InsiderOwn": "19.80", "ShsOutstand": 34340000.0, "PerfWeek": "5.92", "LastUpdated": "2024-05-23", "MarketCap": 184410000.0, "ForwardPE": "", "EPSnextY": "11.77", "InsiderTrans": "0.30", "ShsFloat": 27540000.0, "PerfMonth": "18.28", "Income": -27320000.0, "PEG": "", "EPSnextQ": "-0.24", "InstOwn": "48.61", "ShortFloat": "2.66", "PerfQuarter": "35.61", "Sales": 0.0, "PS": "", "EPSthisY": "27.71", "InstTrans": "1.44", "ShortRatio": "6.09", "PerfHalfY": "1.90", "Booksh": "1.44", "PB": "3.72", "ROA": "-60.15", "ShortInterest": 730000.0, "PerfYear": "-13.53", "Cashsh": "1.93", "PC": "2.78", "EPSnext5Y": "15.00", "ROE": "-109.49", "FiftyTwoWRange": [3.03, 7.8], "PerfYTD": "30.34", "DividendEst": "", "PFCF": "", "EPSpast5Y": "53.91", "ROI": "-55.23", "FiftyTwoWHigh": "-31.15", "Beta": "1.35", "DividendTTM": "", "QuickRatio": "3.29", "Salespast5Y": "0.00", "GrossMargin": "", "FiftyTwoWLow": "77.23", "ATR14": "0.24", "DividendEx-Date": "", "CurrentRatio": "3.29", "EPSYYTTM": "65.82", "OperMargin": "0.00", "RSI14": "69.29", "Volatility": [4.74, 4.91], "Employees": "22", "DebtEq": "0.35", "SalesYYTTM": "", "ProfitMargin": "", "Recom": "1.00", "TargetPrice": "17.25", "OptionShort": true, "LTDebtEq": "0.00", "EPSQQ": "48.33", "Payout": "", "RelVolume": "0.80", "PrevClose": "5.15", "SalesSurprise": "", "EPSSurprise": "-7.57", "SalesQQ": "", "Earnings": "May 09 AMC", "AvgVolume": 120110.0, "Price": "5.37", "SMA20": "12.23", "SMA50": "16.27", "SMA200": "18.75", "Trades": "\n\n", "Volume": "86720", "Change": "4.27"}