{"Sector": "Financial", "Industry": "Closed-End Fund - Equity", "Country": "USA", "Exchange": "NYSE", "Index": "", "PE": "10.09", "EPSttm": "0.81", "InsiderOwn": "", "ShsOutstand": 186490000.0, "PerfWeek": "-1.39", "LastUpdated": "2024-05-23", "MarketCap": 1520000000.0, "ForwardPE": "", "EPSnextY": "", "InsiderTrans": "", "ShsFloat": 186490000.0, "PerfMonth": "1.68", "Income": "", "PEG": "", "EPSnextQ": "", "InstOwn": "20.36", "ShortFloat": "0.02", "PerfQuarter": "2.32", "Sales": 48040000.0, "PS": "31.74", "EPSthisY": "", "InstTrans": "", "ShortRatio": "0.10", "PerfHalfY": "8.75", "Booksh": "8.82", "PB": "0.93", "ROA": "", "ShortInterest": 40000.0, "PerfYear": "1.39", "Cashsh": "", "PC": "", "EPSnext5Y": "", "ROE": "", "FiftyTwoWRange": [6.86, 8.37], "PerfYTD": "6.31", "DividendEst": "", "PFCF": "", "EPSpast5Y": "", "ROI": "", "FiftyTwoWHigh": "-2.34", "Beta": "1.03", "DividendTTM": [0.63, 7.72], "QuickRatio": "", "Salespast5Y": "", "GrossMargin": "", "FiftyTwoWLow": "19.23", "ATR14": "0.06", "DividendEx-Date": "May 14 2024", "CurrentRatio": "", "EPSYYTTM": "", "OperMargin": "", "RSI14": "49.10", "Volatility": [0.52, 0.66], "Employees": "", "DebtEq": "", "SalesYYTTM": "", "ProfitMargin": "", "Recom": "3.00", "TargetPrice": "", "OptionShort": false, "LTDebtEq": "", "EPSQQ": "-10.60", "Payout": "", "RelVolume": "0.69", "PrevClose": "8.28", "SalesSurprise": "", "EPSSurprise": "", "SalesQQ": "13.20", "Earnings": "", "AvgVolume": 446530.0, "Price": "8.18", "SMA20": "-0.12", "SMA50": "0.59", "SMA200": "4.80", "Trades": "\n\n", "Volume": "283083", "Change": "-1.27"}