{"Index": "-", "P/E": "26.71", "EPS (ttm)": "1.68", "Insider Own": "2.10%", "Shs Outstand": "275.52M", "Perf Week": "3.90%", "Market Cap": "12.47B", "Forward P/E": "22.80", "EPS next Y": "8.45%", "Insider Trans": "0.17%", "Shs Float": "236.87M", "Perf Month": "-5.21%", "Income": "461.40M", "PEG": "2.65", "EPS next Q": "0.56", "Inst Own": "70.70%", "Short Float": "1.45%", "Perf Quarter": "-2.44%", "Sales": "2.57B", "P/S": "4.84", "EPS this Y": "15.20%", "Inst Trans": "-0.66%", "Short Ratio": "3.35", "Perf Half Y": "-1.86%", "Book/sh": "13.44", "P/B": "3.33", "ROA": "5.70%", "Target Price": "51.44", "Perf Year": "-4.21%", "Cash/sh": "3.91", "P/C": "11.46", "EPS next 5Y": "10.07%", "ROE": "13.10%", "52W Range": "30.70 - 48.76", "Perf YTD": "-5.57%", "Dividend": "0.37", "P/FCF": "24.57", "EPS past 5Y": "14.70%", "ROI": "9.20%", "52W High": "-8.18%", "Beta": "0.67", "Dividend %": "0.83%", "Quick Ratio": "1.40", "Sales past 5Y": "8.70%", "Gross Margin": "-", "52W Low": "45.83%", "ATR": "1.13", "Employees": "10083", "Current Ratio": "1.40", "Sales Q/Q": "8.90%", "Oper. Margin": "27.00%", "RSI (14)": "46.24", "Volatility": "2.37% 2.27%", "Optionable": "Yes", "Debt/Eq": "0.57", "EPS Q/Q": "15.80%", "Profit Margin": "17.90%", "Rel Volume": "0.77", "Prev Close": "43.91", "Shortable": "Yes", "LT Debt/Eq": "0.55", "Earnings": "Jan 25 AMC", "Payout": "20.20%", "Avg Volume": "1.02M", "Price": "44.77", "Recom": "2.60", "SMA20": "-2.37%", "SMA50": "-2.32%", "SMA200": "2.07%", "Volume": "784,602", "Change": "1.96%"}