{"Sector": "Financial", "Industry": "Exchange Traded Fund", "Country": "USA", "Exchange": "NYSE", "Index": "", "PE": "", "EPSttm": "", "InsiderOwn": "", "ShsOutstand": "", "PerfWeek": "-0.24", "LastUpdated": "2023-10-06", "MarketCap": "", "ForwardPE": "", "EPSnextY": "", "InsiderTrans": "", "ShsFloat": "", "PerfMonth": "-6.40", "Income": "", "PEG": "", "EPSnextQ": "", "InstOwn": "", "ShortFloatRatio": "- / -", "PerfQuarter": "-4.73", "Sales": "", "PS": "", "EPSthisY": "", "InstTrans": "", "ShortInterest": "", "PerfHalfY": "4.93", "Booksh": "", "PB": "", "ROA": "", "TargetPrice": "", "PerfYear": "7.10", "Cashsh": "", "PC": "", "EPSnext5Y": "", "ROE": "", "FiftyTwoWRange": [16.89, 23.05], "PerfYTD": "16.44", "Dividend": "", "PFCF": "", "EPSpast5Y": "", "ROI": "", "FiftyTwoWHigh": "-11.74", "Beta": "1.31", "DividendPercent": "", "QuickRatio": "", "Salespast5Y": "", "GrossMargin": "", "FiftyTwoWLow": "20.44", "ATR": "0.26", "Employees": "", "CurrentRatio": "", "SalesQQ": "", "OperMargin": "", "RSI14": "43.93", "Volatility": [0.38, 0.38], "Optionable": true, "DebtEq": "", "EPSQQ": "", "ProfitMargin": "", "RelVolume": "0.47", "PrevClose": "20.29", "Shortable": true, "LTDebtEq": "", "Earnings": "", "Payout": "", "AvgVolume": 1350.0, "Price": "20.34", "Recom": "", "SMA20": "-1.42", "SMA50": "-4.01", "SMA200": "1.54", "Volume": "635", "Change": "0.25"}