{"Sector": "Financial", "Industry": "Insurance - Property & Casualty", "Country": "USA", "Exchange": "NASD", "Index": "S&P 500", "PE": "11.84", "EPSttm": "8.56", "InsiderOwn": "2.05", "ShsOutstand": 157100000.0, "PerfWeek": "-2.28", "LastUpdated": "2023-10-06", "MarketCap": 15900000000.0, "ForwardPE": "16.58", "EPSnextY": "21.80", "InsiderTrans": "-0.54", "ShsFloat": 153630000.0, "PerfMonth": "-3.04", "Income": 1350000000.0, "PEG": "0.72", "EPSnextQ": "1.10", "InstOwn": "66.52", "ShortFloatRatio": "0.77 / 1.79", "PerfQuarter": "3.23", "Sales": 9370000000.0, "PS": "1.70", "EPSthisY": "18.36", "InstTrans": "2.18", "ShortInterest": 1180000.0, "PerfHalfY": "-8.93", "Booksh": "70.34", "PB": "1.44", "ROA": "4.58", "TargetPrice": "122.80", "PerfYear": "5.35", "Cashsh": "", "PC": "", "EPSnext5Y": "16.50", "ROE": "12.55", "FiftyTwoWRange": [93.64, 130.66], "PerfYTD": "-1.03", "Dividend": "3.00", "PFCF": "7.54", "EPSpast5Y": "", "ROI": "11.40", "FiftyTwoWHigh": "-22.44", "Beta": "0.65", "DividendPercent": "2.96", "QuickRatio": "", "Salespast5Y": "6.37", "GrossMargin": "", "FiftyTwoWLow": "8.22", "ATR": "1.79", "Employees": "5148", "CurrentRatio": "0.55", "SalesQQ": "217.68", "OperMargin": "18.10", "RSI14": "37.27", "Volatility": [2.0, 1.6], "Optionable": true, "DebtEq": "0.08", "EPSQQ": "", "ProfitMargin": "14.45", "RelVolume": "1.02", "PrevClose": "100.88", "Shortable": true, "LTDebtEq": "0.08", "Earnings": "Jul 27 AMC", "Payout": "", "AvgVolume": 660270.0, "Price": "101.34", "Recom": "2.25", "SMA20": "-3.93", "SMA50": "-4.31", "SMA200": "-5.19", "Volume": "672274", "Change": "0.46"}