{"Sector": "Technology", "Industry": "Communication Equipment", "Country": "Israel", "Exchange": "NASD", "Index": "", "PE": "49.72", "EPSttm": "0.05", "InsiderOwn": "17.76", "ShsOutstand": 85420000.0, "PerfWeek": "-1.10", "LastUpdated": "2024-05-26", "MarketCap": 231230000.0, "ForwardPE": "6.59", "EPSnextY": "32.26", "InsiderTrans": "0.00", "ShsFloat": 70430000.0, "PerfMonth": "-1.46", "Income": 4660000.0, "PEG": "3.31", "EPSnextQ": "0.06", "InstOwn": "14.85", "ShortFloat": "0.82", "PerfQuarter": "-11.48", "Sales": 352270000.0, "PS": "0.66", "EPSthisY": "55.00", "InstTrans": "50.75", "ShortRatio": "1.08", "PerfHalfY": "51.69", "Booksh": "1.58", "PB": "1.71", "ROA": "1.61", "ShortInterest": 580000.0, "PerfYear": "50.00", "Cashsh": "0.34", "PC": "8.03", "EPSnext5Y": "15.00", "ROE": "3.61", "FiftyTwoWRange": [1.56, 3.38], "PerfYTD": "25.00", "DividendEst": "", "PFCF": "10.07", "EPSpast5Y": "-24.32", "ROI": "3.14", "FiftyTwoWHigh": "-20.12", "Beta": "1.41", "DividendTTM": "", "QuickRatio": "1.19", "Salespast5Y": "0.97", "GrossMargin": "35.06", "FiftyTwoWLow": "73.08", "ATR14": "0.12", "DividendEx-Date": "", "CurrentRatio": "1.70", "EPSYYTTM": "247.72", "OperMargin": "6.98", "RSI14": "44.23", "Volatility": [3.88, 4.36], "Employees": "1407", "DebtEq": "0.35", "SalesYYTTM": "14.28", "ProfitMargin": "1.32", "Recom": "1.00", "TargetPrice": "5.25", "OptionShort": true, "LTDebtEq": "0.10", "EPSQQ": "-80.17", "Payout": "0.00", "RelVolume": "0.44", "PrevClose": "2.66", "SalesSurprise": "-2.48", "EPSSurprise": "0.00", "SalesQQ": "6.10", "Earnings": "May 07 BMO", "AvgVolume": 535590.0, "Price": "2.70", "SMA20": "-3.35", "SMA50": "-7.48", "SMA200": "15.95", "Trades": "\n\n", "Volume": "235546", "Change": "1.50"}