{"Sector": "Technology", "Industry": "Software - Infrastructure", "Country": "Israel", "Index": "", "PE": "", "EPSttm": "-3.09", "InsiderOwn": "0.02", "ShsOutstand": 40840000.0, "PerfWeek": "1.49", "LastUpdated": "2023-01-13", "MarketCap": 4920000000.0, "ForwardPE": "9205.38", "EPSnextY": "102.10", "InsiderTrans": "0.00", "ShsFloat": 40070000.0, "PerfMonth": "-13.07", "Income": -125100000.0, "PEG": "", "EPSnextQ": "-0.10", "InstOwn": "96.10", "ShortFloatRatio": "5.53 / 4.58", "PerfQuarter": "-14.82", "Sales": 573900000.0, "PS": "8.57", "EPSthisY": "-245.50", "InstTrans": "2.94", "ShortInterest": 2220000.0, "PerfHalfY": "-4.73", "Booksh": "16.07", "PB": "7.45", "ROA": "-7.30", "TargetPrice": "176.15", "PerfYear": "-25.98", "Cashsh": "23.11", "PC": "5.18", "EPSnext5Y": "", "ROE": "-18.40", "FiftyTwoWRange": [100.35, 180.01], "PerfYTD": "-7.70", "Dividend": "", "PFCF": "125.73", "EPSpast5Y": "-36.30", "ROI": "-5.70", "FiftyTwoWHigh": "-33.78", "Beta": "1.05", "DividendPercent": "", "QuickRatio": "2.70", "Salespast5Y": "18.30", "GrossMargin": "79.60", "FiftyTwoWLow": "18.79", "ATR": "5.41", "Employees": "2140", "CurrentRatio": "2.70", "SalesQQ": "25.60", "OperMargin": "-23.40", "RSI14": "37.11", "Volatility": [3.34, 3.69], "Optionable": true, "DebtEq": "0.87", "EPSQQ": "-9.70", "ProfitMargin": "-21.80", "RelVolume": "0.90", "PrevClose": "119.67", "Shortable": true, "LTDebtEq": "0.87", "Earnings": "Nov 03 BMO", "Payout": "", "AvgVolume": 483690.0, "Price": "119.21", "Recom": "1.70", "SMA20": "-5.34", "SMA50": "-14.12", "SMA200": "-16.87", "Volume": "159808", "Change": "-0.39"}