{"Sector": "Financial", "Industry": "Exchange Traded Fund", "Country": "USA", "Exchange": "NYSE", "Index": "", "PE": "", "EPSttm": "", "InsiderOwn": "", "ShsOutstand": "", "PerfWeek": "-1.36", "LastUpdated": "2023-10-06", "MarketCap": "", "ForwardPE": "", "EPSnextY": "", "InsiderTrans": "", "ShsFloat": "", "PerfMonth": "-3.40", "Income": "", "PEG": "", "EPSnextQ": "", "InstOwn": "", "ShortFloatRatio": "- / -", "PerfQuarter": "-2.43", "Sales": "", "PS": "", "EPSthisY": "", "InstTrans": "", "ShortInterest": "", "PerfHalfY": "-3.65", "Booksh": "", "PB": "", "ROA": "", "TargetPrice": "", "PerfYear": "17.86", "Cashsh": "", "PC": "", "EPSnext5Y": "", "ROE": "", "FiftyTwoWRange": [23.99, 32.77], "PerfYTD": "8.94", "Dividend": "6.15", "PFCF": "", "EPSpast5Y": "", "ROI": "", "FiftyTwoWHigh": "-7.65", "Beta": "0.89", "DividendPercent": "20.33", "QuickRatio": "", "Salespast5Y": "", "GrossMargin": "", "FiftyTwoWLow": "26.17", "ATR": "0.28", "Employees": "", "CurrentRatio": "", "SalesQQ": "", "OperMargin": "", "RSI14": "35.16", "Volatility": [0.89, 0.65], "Optionable": true, "DebtEq": "", "EPSQQ": "", "ProfitMargin": "", "RelVolume": "1.54", "PrevClose": "30.26", "Shortable": true, "LTDebtEq": "", "Earnings": "", "Payout": "", "AvgVolume": 54620.0, "Price": "30.26", "Recom": "", "SMA20": "-2.33", "SMA50": "-3.71", "SMA200": "-3.22", "Volume": "83951", "Change": "0.01"}