{"Index": "", "PE": "", "EPSttm": "", "InsiderOwn": "", "ShsOutstand": 18690000.0, "PerfWeek": "4.93", "LastUpdated": "2021-02-09", "MarketCap": 155130000.0, "ForwardPE": "", "EPSnextY": "", "InsiderTrans": "", "ShsFloat": "", "PerfMonth": "2.34", "Income": "", "PEG": "", "EPSnextQ": "", "InstOwn": "40.01", "ShortFloat": "", "PerfQuarter": "28.48", "Sales": "", "PS": "", "EPSthisY": "", "InstTrans": "", "ShortRatio": "0.03", "PerfHalfY": "28.09", "Booksh": "", "PB": "", "ROA": "", "TargetPrice": "", "PerfYear": "-26.94", "Cashsh": "", "PC": "", "EPSnext5Y": "", "ROE": "", "FiftyTwoWRange": [3.11, 11.57], "PerfYTD": "7.10", "Dividend": "0.58", "PFCF": "", "EPSpast5Y": "", "ROI": "", "FiftyTwoWHigh": "-28.52", "Beta": "", "DividendPercent": "6.99", "QuickRatio": "", "Salespast5Y": "", "GrossMargin": "", "FiftyTwoWLow": "165.92", "ATR": "0.18", "Employees": "", "CurrentRatio": "", "SalesQQ": "", "OperMargin": "", "RSI14": "61.02", "Volatility": [1.25, 1.96], "Optionable": false, "DebtEq": "", "EPSQQ": "", "ProfitMargin": "", "RelVolume": "0.27", "PrevClose": "8.30", "Shortable": true, "LTDebtEq": "", "Earnings": "", "Payout": "", "AvgVolume": 122420.0, "Price": "8.27", "Recom": "", "SMA20": "1.53", "SMA50": "4.03", "SMA200": "23.36", "Volume": "6444", "Change": "-0.36"}