{"Index": "", "PE": "8.14", "EPSttm": "1.06", "InsiderOwn": "41.80", "ShsOutstand": 7280000.0, "PerfWeek": "0.70", "LastUpdated": "2021-02-08", "MarketCap": 64030000.0, "ForwardPE": "", "EPSnextY": "", "InsiderTrans": "-0.32", "ShsFloat": 3800000.0, "PerfMonth": "0.82", "Income": 7800000.0, "PEG": "", "EPSnextQ": "", "InstOwn": "8.70", "ShortFloat": "2.85", "PerfQuarter": "4.23", "Sales": 33400000.0, "PS": "1.92", "EPSthisY": "-25.10", "InstTrans": "", "ShortRatio": "7.18", "PerfHalfY": "6.15", "Booksh": "10.74", "PB": "0.80", "ROA": "8.10", "TargetPrice": "", "PerfYear": "-17.38", "Cashsh": "1.35", "PC": "6.40", "EPSnext5Y": "", "ROE": "10.20", "FiftyTwoWRange": [5.68, 11.15], "PerfYTD": "1.35", "Dividend": "0.55", "PFCF": "10.01", "EPSpast5Y": "-3.60", "ROI": "10.50", "FiftyTwoWHigh": "4.93", "Beta": "0.99", "DividendPercent": "6.37", "QuickRatio": "2.60", "Salespast5Y": "-5.70", "GrossMargin": "77.30", "FiftyTwoWLow": "105.80", "ATR": "0.22", "Employees": "19", "CurrentRatio": "2.60", "SalesQQ": "-27.50", "OperMargin": "33.90", "RSI14": "82.57", "Volatility": [1.55, 2.53], "Optionable": false, "DebtEq": "0.00", "EPSQQ": "-37.10", "ProfitMargin": "23.50", "RelVolume": "44.12", "PrevClose": "8.63", "Shortable": true, "LTDebtEq": "0.00", "Earnings": "", "Payout": "51.70", "AvgVolume": 15110.0, "Price": "11.70", "Recom": "1.00", "SMA20": "33.69", "SMA50": "32.94", "SMA200": "37.86", "Volume": "218421", "Change": "35.57"}