{"Sector": "Healthcare", "Industry": "Drug Manufacturers - Specialty & Generic", "Country": "Canada", "Exchange": "NASD", "Index": "", "PE": "", "EPSttm": "-0.26", "InsiderOwn": "16.76", "ShsOutstand": 39380000.0, "PerfWeek": "13.87", "LastUpdated": "2024-05-23", "MarketCap": 14510000.0, "ForwardPE": "", "EPSnextY": "45.45", "InsiderTrans": "0.00", "ShsFloat": 33660000.0, "PerfMonth": "-21.89", "Income": -10180000.0, "PEG": "", "EPSnextQ": "-0.06", "InstOwn": "1.64", "ShortFloat": "0.99", "PerfQuarter": "-62.64", "Sales": 0.0, "PS": "", "EPSthisY": "52.17", "InstTrans": "", "ShortRatio": "1.04", "PerfHalfY": "-73.43", "Booksh": "0.30", "PB": "1.21", "ROA": "-45.31", "ShortInterest": 330000.0, "PerfYear": "-67.54", "Cashsh": "0.05", "PC": "6.94", "EPSnext5Y": "", "ROE": "-61.89", "FiftyTwoWRange": [0.31, 1.68], "PerfYTD": "-61.00", "DividendEst": "", "PFCF": "", "EPSpast5Y": "31.10", "ROI": "-84.59", "FiftyTwoWHigh": "-78.65", "Beta": "0.61", "DividendTTM": "", "QuickRatio": "2.34", "Salespast5Y": "0.00", "GrossMargin": "", "FiftyTwoWLow": "16.99", "ATR14": "0.04", "DividendEx-Date": "", "CurrentRatio": "2.34", "EPSYYTTM": "63.92", "OperMargin": "0.00", "RSI14": "38.59", "Volatility": [8.07, 12.11], "Employees": "", "DebtEq": "0.05", "SalesYYTTM": "", "ProfitMargin": "", "Recom": "1.00", "TargetPrice": "2.60", "OptionShort": true, "LTDebtEq": "0.00", "EPSQQ": "81.22", "Payout": "", "RelVolume": "0.32", "PrevClose": "0.34", "SalesSurprise": "", "EPSSurprise": "0.00", "SalesQQ": "", "Earnings": "May 16 BMO", "AvgVolume": 322770.0, "Price": "0.36", "SMA20": "-3.11", "SMA50": "-31.42", "SMA200": "-61.60", "Trades": "\n\n", "Volume": "99440", "Change": "5.50"}