{"Sector": "Financial", "Industry": "Exchange Traded Fund", "Country": "USA", "Index": "", "PE": "", "EPSttm": "", "InsiderOwn": "", "ShsOutstand": "", "PerfWeek": "0.35", "LastUpdated": "2023-01-13", "MarketCap": "", "ForwardPE": "", "EPSnextY": "", "InsiderTrans": "", "ShsFloat": "", "PerfMonth": "0.25", "Income": "", "PEG": "", "EPSnextQ": "", "InstOwn": "", "ShortFloatRatio": "- / -", "PerfQuarter": "1.19", "Sales": "", "PS": "", "EPSthisY": "", "InstTrans": "", "ShortInterest": "", "PerfHalfY": "-0.63", "Booksh": "", "PB": "", "ROA": "", "TargetPrice": "", "PerfYear": "-3.00", "Cashsh": "", "PC": "", "EPSnext5Y": "", "ROE": "", "FiftyTwoWRange": [25.41, 26.71], "PerfYTD": "0.56", "Dividend": "0.31", "PFCF": "", "EPSpast5Y": "", "ROI": "", "FiftyTwoWHigh": "-3.11", "Beta": "", "DividendPercent": "1.19", "QuickRatio": "", "Salespast5Y": "", "GrossMargin": "", "FiftyTwoWLow": "1.85", "ATR": "0.05", "Employees": "", "CurrentRatio": "", "SalesQQ": "", "OperMargin": "", "RSI14": "68.46", "Volatility": [0.17, 0.17], "Optionable": false, "DebtEq": "", "EPSQQ": "", "ProfitMargin": "", "RelVolume": "0.06", "PrevClose": "25.90", "Shortable": false, "LTDebtEq": "", "Earnings": "", "Payout": "", "AvgVolume": 155380.0, "Price": "25.88", "Recom": "", "SMA20": "0.39", "SMA50": "0.55", "SMA200": "0.28", "Volume": "3879", "Change": "-0.06"}