{"Sector": "Financial", "Industry": "Exchange Traded Fund", "Country": "USA", "Index": "", "PE": "", "EPSttm": "", "InsiderOwn": "", "ShsOutstand": "", "PerfWeek": "9.65", "LastUpdated": "2023-01-13", "MarketCap": "", "ForwardPE": "", "EPSnextY": "", "InsiderTrans": "", "ShsFloat": "", "PerfMonth": "2.31", "Income": "", "PEG": "", "EPSnextQ": "", "InstOwn": "", "ShortFloatRatio": "- / -", "PerfQuarter": "20.06", "Sales": "", "PS": "", "EPSthisY": "", "InstTrans": "", "ShortInterest": "", "PerfHalfY": "11.08", "Booksh": "", "PB": "", "ROA": "", "TargetPrice": "", "PerfYear": "7.65", "Cashsh": "", "PC": "", "EPSnext5Y": "", "ROE": "", "FiftyTwoWRange": [16.34, 23.85], "PerfYTD": "7.05", "Dividend": "0.18", "PFCF": "", "EPSpast5Y": "", "ROI": "", "FiftyTwoWHigh": "-11.47", "Beta": "", "DividendPercent": "0.83", "QuickRatio": "", "Salespast5Y": "", "GrossMargin": "", "FiftyTwoWLow": "29.18", "ATR": "0.45", "Employees": "", "CurrentRatio": "", "SalesQQ": "", "OperMargin": "", "RSI14": "61.53", "Volatility": [2.29, 2.08], "Optionable": true, "DebtEq": "", "EPSQQ": "", "ProfitMargin": "", "RelVolume": "0.64", "PrevClose": "21.25", "Shortable": true, "LTDebtEq": "", "Earnings": "", "Payout": "", "AvgVolume": 9220000.0, "Price": "21.11", "Recom": "", "SMA20": "4.63", "SMA50": "4.30", "SMA200": "4.61", "Volume": "2469562", "Change": "-0.64"}