{"Sector": "Financial", "Industry": "Exchange Traded Fund", "Country": "USA", "Exchange": "NYSE", "Index": "", "PE": "", "EPSttm": "", "InsiderOwn": "", "ShsOutstand": "", "PerfWeek": "-3.16", "LastUpdated": "2023-10-06", "MarketCap": "", "ForwardPE": "", "EPSnextY": "", "InsiderTrans": "", "ShsFloat": "", "PerfMonth": "-7.00", "Income": "", "PEG": "", "EPSnextQ": "", "InstOwn": "", "ShortFloatRatio": "- / -", "PerfQuarter": "-6.38", "Sales": "", "PS": "", "EPSthisY": "", "InstTrans": "", "ShortInterest": "", "PerfHalfY": "9.50", "Booksh": "", "PB": "", "ROA": "", "TargetPrice": "", "PerfYear": "0.16", "Cashsh": "", "PC": "", "EPSnext5Y": "", "ROE": "", "FiftyTwoWRange": [23.62, 36.7], "PerfYTD": "24.07", "Dividend": "", "PFCF": "", "EPSpast5Y": "", "ROI": "", "FiftyTwoWHigh": "-16.43", "Beta": "1.22", "DividendPercent": "", "QuickRatio": "", "Salespast5Y": "", "GrossMargin": "", "FiftyTwoWLow": "29.85", "ATR": "0.70", "Employees": "", "CurrentRatio": "", "SalesQQ": "", "OperMargin": "", "RSI14": "39.25", "Volatility": [2.16, 1.84], "Optionable": true, "DebtEq": "", "EPSQQ": "", "ProfitMargin": "", "RelVolume": "0.40", "PrevClose": "31.16", "Shortable": true, "LTDebtEq": "", "Earnings": "", "Payout": "", "AvgVolume": 81760.0, "Price": "30.67", "Recom": "", "SMA20": "-4.36", "SMA50": "-6.13", "SMA200": "2.43", "Volume": "32911", "Change": "-1.57"}