{"Index": "", "PE": "", "EPSttm": "-2.89", "InsiderOwn": "", "ShsOutstand": 341610000.0, "PerfWeek": "7.74", "LastUpdated": "2021-02-08", "MarketCap": 1850000000.0, "ForwardPE": "41.77", "EPSnextY": "", "InsiderTrans": "", "ShsFloat": 101080000.0, "PerfMonth": "4.62", "Income": -988100000.0, "PEG": "", "EPSnextQ": "", "InstOwn": "0.20", "ShortFloat": "0.02", "PerfQuarter": "38.87", "Sales": 2150000000.0, "PS": "0.86", "EPSthisY": "-26.10", "InstTrans": "0.15", "ShortRatio": "0.36", "PerfHalfY": "9.70", "Booksh": "9.94", "PB": "0.55", "ROA": "-2.00", "TargetPrice": "5.10", "PerfYear": "-27.11", "Cashsh": "37.82", "PC": "0.14", "EPSnext5Y": "", "ROE": "-25.00", "FiftyTwoWRange": [3.01, 7.55], "PerfYTD": "9.70", "Dividend": "0.43", "PFCF": "0.94", "EPSpast5Y": "-18.40", "ROI": "3.60", "FiftyTwoWHigh": "-26.63", "Beta": "1.22", "DividendPercent": "7.92", "QuickRatio": "", "Salespast5Y": "5.40", "GrossMargin": "", "FiftyTwoWLow": "84.02", "ATR": "0.20", "Employees": "3811", "CurrentRatio": "", "SalesQQ": "-23.40", "OperMargin": "25.50", "RSI14": "59.63", "Volatility": [3.33, 3.58], "Optionable": false, "DebtEq": "4.44", "EPSQQ": "-138.40", "ProfitMargin": "-46.00", "RelVolume": "0.04", "PrevClose": "5.43", "Shortable": true, "LTDebtEq": "4.13", "Earnings": "", "Payout": "", "AvgVolume": 47020.0, "Price": "5.54", "Recom": "4.00", "SMA20": "4.16", "SMA50": "11.54", "SMA200": "25.84", "Volume": "682", "Change": "2.01"}