{"Sector": "Financial", "Industry": "Exchange Traded Fund", "Country": "USA", "Exchange": "NYSE", "Index": "", "PE": "", "EPSttm": "", "InsiderOwn": "", "ShsOutstand": "", "PerfWeek": "-0.85", "LastUpdated": "2023-10-06", "MarketCap": "", "ForwardPE": "", "EPSnextY": "", "InsiderTrans": "", "ShsFloat": "", "PerfMonth": "-3.06", "Income": "", "PEG": "", "EPSnextQ": "", "InstOwn": "", "ShortFloatRatio": "- / -", "PerfQuarter": "-2.59", "Sales": "", "PS": "", "EPSthisY": "", "InstTrans": "", "ShortInterest": "", "PerfHalfY": "-11.96", "Booksh": "", "PB": "", "ROA": "", "TargetPrice": "", "PerfYear": "-5.52", "Cashsh": "", "PC": "", "EPSnext5Y": "", "ROE": "", "FiftyTwoWRange": [34.64, 48.1], "PerfYTD": "-1.07", "Dividend": "10.00", "PFCF": "", "EPSpast5Y": "", "ROI": "", "FiftyTwoWHigh": "-24.99", "Beta": "0.80", "DividendPercent": "27.71", "QuickRatio": "", "Salespast5Y": "", "GrossMargin": "", "FiftyTwoWLow": "4.16", "ATR": "0.46", "Employees": "", "CurrentRatio": "", "SalesQQ": "", "OperMargin": "", "RSI14": "41.91", "Volatility": [0.7, 0.85], "Optionable": true, "DebtEq": "", "EPSQQ": "", "ProfitMargin": "", "RelVolume": "0.83", "PrevClose": "36.32", "Shortable": true, "LTDebtEq": "", "Earnings": "", "Payout": "", "AvgVolume": 94280.0, "Price": "36.08", "Recom": "", "SMA20": "-1.44", "SMA50": "-3.83", "SMA200": "-6.53", "Volume": "77849", "Change": "-0.66"}