{"Index": "-", "P/E": "-", "EPS (ttm)": "-", "Insider Own": "-", "Shs Outstand": "-", "Perf Week": "5.36%", "Market Cap": "-", "Forward P/E": "-", "EPS next Y": "-", "Insider Trans": "-", "Shs Float": "-", "Perf Month": "2.45%", "Income": "-", "PEG": "-", "EPS next Q": "-", "Inst Own": "-", "Short Float": "-", "Perf Quarter": "16.45%", "Sales": "-", "P/S": "-", "EPS this Y": "-", "Inst Trans": "-", "Short Ratio": "-", "Perf Half Y": "19.27%", "Book/sh": "-", "P/B": "-", "ROA": "-", "Target Price": "-", "Perf Year": "15.35%", "Cash/sh": "-", "P/C": "-", "EPS next 5Y": "-", "ROE": "-", "52W Range": "35.00 - 65.10", "Perf YTD": "4.61%", "Dividend": "0.95", "P/FCF": "-", "EPS past 5Y": "-", "ROI": "-", "52W High": "-0.37%", "Beta": "-", "Dividend %": "1.46%", "Quick Ratio": "-", "Sales past 5Y": "-", "Gross Margin": "-", "52W Low": "85.31%", "ATR": "0.89", "Employees": "-", "Current Ratio": "-", "Sales Q/Q": "-", "Oper. Margin": "-", "RSI (14)": "61.42", "Volatility": "1.13% 1.11%", "Optionable": "Yes", "Debt/Eq": "-", "EPS Q/Q": "-", "Profit Margin": "-", "Rel Volume": "0.83", "Prev Close": "64.45", "Shortable": "Yes", "LT Debt/Eq": "-", "Earnings": "-", "Payout": "-", "Avg Volume": "332.27K", "Price": "64.86", "Recom": "-", "SMA20": "1.77%", "SMA50": "3.45%", "SMA200": "15.53%", "Volume": "274,652", "Change": "0.64%"}