{"Index": "", "PE": "", "EPSttm": "", "InsiderOwn": "", "ShsOutstand": "", "PerfWeek": "6.55", "LastUpdated": "2021-02-08", "MarketCap": "", "ForwardPE": "", "EPSnextY": "", "InsiderTrans": "", "ShsFloat": "", "PerfMonth": "5.58", "Income": "", "PEG": "", "EPSnextQ": "", "InstOwn": "", "ShortFloat": "", "PerfQuarter": "34.56", "Sales": "", "PS": "", "EPSthisY": "", "InstTrans": "", "ShortRatio": "", "PerfHalfY": "48.51", "Booksh": "", "PB": "", "ROA": "", "TargetPrice": "", "PerfYear": "68.71", "Cashsh": "", "PC": "", "EPSnext5Y": "", "ROE": "", "FiftyTwoWRange": [16.55, 45.01], "PerfYTD": "9.56", "Dividend": "0.09", "PFCF": "", "EPSpast5Y": "", "ROI": "", "FiftyTwoWHigh": "-0.27", "Beta": "", "DividendPercent": "0.20", "QuickRatio": "", "Salespast5Y": "", "GrossMargin": "", "FiftyTwoWLow": "171.20", "ATR": "0.71", "Employees": "", "CurrentRatio": "", "SalesQQ": "", "OperMargin": "", "RSI14": "63.59", "Volatility": [1.03, 1.15], "Optionable": false, "DebtEq": "", "EPSQQ": "", "ProfitMargin": "", "RelVolume": "2.41", "PrevClose": "44.64", "Shortable": false, "LTDebtEq": "", "Earnings": "", "Payout": "", "AvgVolume": 5050.0, "Price": "44.89", "Recom": "", "SMA20": "1.99", "SMA50": "8.94", "SMA200": "39.36", "Volume": "4185", "Change": "0.56"}