{"Sector": "", "Industry": "", "Country": "", "Exchange": "", "Index": "", "PE": "", "EPSttm": "-2.61", "InsiderOwn": "0.04", "ShsOutstand": 36060000.0, "PerfWeek": "-3.47", "LastUpdated": "2024-05-14", "MarketCap": 3010000.0, "ForwardPE": "", "EPSnextY": "94.12", "InsiderTrans": "0.00", "ShsFloat": 36050000.0, "PerfMonth": "2.45", "Income": -18550000.0, "PEG": "", "EPSnextQ": "-0.04", "InstOwn": "3.30", "ShortFloat": "0.38", "PerfQuarter": "-39.10", "Sales": 14230000.0, "PS": "0.21", "EPSthisY": "95.71", "InstTrans": "2.32", "ShortRatio": "0.06", "PerfHalfY": "-73.92", "Booksh": "-0.04", "PB": "", "ROA": "-108.92", "ShortInterest": 140000.0, "PerfYear": "-91.41", "Cashsh": "0.05", "PC": "1.65", "EPSnext5Y": "", "ROE": "-242.90", "FiftyTwoWRange": [0.06, 1.28], "PerfYTD": "-59.07", "DividendEst": "", "PFCF": "", "EPSpast5Y": "24.47", "ROI": "-1544.71", "FiftyTwoWHigh": "-93.48", "Beta": "1.86", "DividendTTM": "", "QuickRatio": "0.75", "Salespast5Y": "9.88", "GrossMargin": "54.47", "FiftyTwoWLow": "28.46", "ATR14": "0.01", "DividendEx-Date": "", "CurrentRatio": "0.92", "EPSYYTTM": "61.13", "OperMargin": "-34.01", "RSI14": "42.54", "Volatility": [10.66, 12.77], "Employees": "26", "DebtEq": "15.12", "SalesYYTTM": "4.36", "ProfitMargin": "-130.34", "Recom": "1.00", "TargetPrice": "1.68", "OptionShort": false, "LTDebtEq": "6.50", "EPSQQ": "82.95", "Payout": "", "RelVolume": "0.74", "PrevClose": "0.08", "SalesSurprise": "-20.27", "EPSSurprise": "0.00", "SalesQQ": "-15.78", "Earnings": "May 09 AMC", "AvgVolume": 2380000.0, "Price": "0.08", "SMA20": "0.20", "SMA50": "-21.42", "SMA200": "-71.82", "Trades": "\n\n", "Volume": "1046992", "Change": "3.47"}