{"Sector": "Financial", "Industry": "Asset Management", "Country": "USA", "Index": "", "PE": "7.68", "EPSttm": "2.27", "InsiderOwn": "5.30", "ShsOutstand": 24300000.0, "PerfWeek": "11.67", "LastUpdated": "2023-01-13", "MarketCap": 422440000.0, "ForwardPE": "5.87", "EPSnextY": "8.12", "InsiderTrans": "0.00", "ShsFloat": 23030000.0, "PerfMonth": "-5.17", "Income": 54600000.0, "PEG": "2.56", "EPSnextQ": "0.60", "InstOwn": "15.90", "ShortFloatRatio": "7.65 / 10.00", "PerfQuarter": "14.01", "Sales": 151700000.0, "PS": "2.78", "EPSthisY": "132.20", "InstTrans": "-10.97", "ShortInterest": 1760000.0, "PerfHalfY": "-8.99", "Booksh": "16.12", "PB": "1.08", "ROA": "5.30", "TargetPrice": "17.00", "PerfYear": "-38.49", "Cashsh": "0.31", "PC": "57.09", "EPSnext5Y": "3.00", "ROE": "13.70", "FiftyTwoWRange": [14.75, 28.45], "PerfYTD": "7.20", "Dividend": "2.80", "PFCF": "", "EPSpast5Y": "14.50", "ROI": "8.90", "FiftyTwoWHigh": "-36.34", "Beta": "1.29", "DividendPercent": "16.07", "QuickRatio": "", "Salespast5Y": "20.70", "GrossMargin": "", "FiftyTwoWLow": "22.78", "ATR": "0.69", "Employees": "104", "CurrentRatio": "", "SalesQQ": "20.80", "OperMargin": "42.30", "RSI14": "61.46", "Volatility": [3.28, 4.34], "Optionable": true, "DebtEq": "1.39", "EPSQQ": "-36.60", "ProfitMargin": "36.00", "RelVolume": "2.67", "PrevClose": "17.42", "Shortable": true, "LTDebtEq": "1.39", "Earnings": "Nov 07 AMC", "Payout": "136.60", "AvgVolume": 176260.0, "Price": "18.11", "Recom": "3.00", "SMA20": "8.13", "SMA50": "7.46", "SMA200": "-10.61", "Volume": "208470", "Change": "3.96"}