{"Sector": "", "Industry": "", "Country": "", "Exchange": "", "Index": "RUT", "PE": "17.44", "EPSttm": "2.52", "InsiderOwn": "0.52", "ShsOutstand": 98820000.0, "PerfWeek": "-2.05", "LastUpdated": "2024-05-14", "MarketCap": 4340000000.0, "ForwardPE": "15.37", "EPSnextY": "-1.83", "InsiderTrans": "-1.26", "ShsFloat": 98310000.0, "PerfMonth": "5.66", "Income": 248780000.0, "PEG": "2.91", "EPSnextQ": "-0.03", "InstOwn": "71.81", "ShortFloat": "2.17", "PerfQuarter": "8.05", "Sales": 1690000000.0, "PS": "2.56", "EPSthisY": "7.84", "InstTrans": "1.50", "ShortRatio": "4.50", "PerfHalfY": "7.07", "Booksh": "22.07", "PB": "1.99", "ROA": "3.84", "ShortInterest": 2130000.0, "PerfYear": "-12.66", "Cashsh": "0.25", "PC": "178.29", "EPSnext5Y": "6.00", "ROE": "11.90", "FiftyTwoWRange": [38.92, 50.72], "PerfYTD": "-1.45", "DividendEst": [1.68, 3.83], "PFCF": "", "EPSpast5Y": "0.51", "ROI": "4.92", "FiftyTwoWHigh": "-13.38", "Beta": "0.63", "DividendTTM": [1.65, 3.76], "QuickRatio": "0.56", "Salespast5Y": "-4.77", "GrossMargin": "19.59", "FiftyTwoWLow": "12.88", "ATR14": "0.79", "DividendEx-Date": "Jun 12 2024", "CurrentRatio": "0.70", "EPSYYTTM": "-16.59", "OperMargin": "19.59", "RSI14": "55.05", "Volatility": [2.06, 1.83], "Employees": "1350", "DebtEq": "1.48", "SalesYYTTM": "-36.45", "ProfitMargin": "14.69", "Recom": "2.50", "TargetPrice": "45.67", "OptionShort": true, "LTDebtEq": "1.32", "EPSQQ": "7.88", "Payout": "58.64", "RelVolume": "0.33", "PrevClose": "44.12", "SalesSurprise": "-4.57", "EPSSurprise": "12.57", "SalesQQ": "3.89", "Earnings": "May 07 BMO", "AvgVolume": 474770.0, "Price": "43.93", "SMA20": "0.68", "SMA50": "2.52", "SMA200": "3.08", "Trades": "\n\n", "Volume": "91653", "Change": "-0.42"}