{"Sector": "Healthcare", "Industry": "Diagnostics & Research", "Country": "USA", "Exchange": "NASD", "Index": "", "PE": "", "EPSttm": "-13.27", "InsiderOwn": "22.55", "ShsOutstand": 25600000.0, "PerfWeek": "-23.23", "LastUpdated": "2023-10-06", "MarketCap": 61360000.0, "ForwardPE": "", "EPSnextY": "82.09", "InsiderTrans": "0.00", "ShsFloat": 19970000.0, "PerfMonth": "-29.59", "Income": -339630000.0, "PEG": "", "EPSnextQ": "-0.17", "InstOwn": "30.61", "ShortFloatRatio": "6.66 / 2.95", "PerfQuarter": "-52.50", "Sales": 582150000.0, "PS": "0.11", "EPSthisY": "77.63", "InstTrans": "-9.10", "ShortInterest": 1330000.0, "PerfHalfY": "-41.67", "Booksh": "10.71", "PB": "0.22", "ROA": "-33.58", "TargetPrice": "15.06", "PerfYear": "-87.86", "Cashsh": "0.86", "PC": "2.76", "EPSnext5Y": "", "ROE": "-76.34", "FiftyTwoWRange": [2.34, 23.37], "PerfYTD": "-51.82", "Dividend": "", "PFCF": "", "EPSpast5Y": "", "ROI": "-49.97", "FiftyTwoWHigh": "-89.82", "Beta": "2.59", "DividendPercent": "", "QuickRatio": "1.03", "Salespast5Y": "165.89", "GrossMargin": "21.61", "FiftyTwoWLow": "1.71", "ATR": "0.22", "Employees": "2099", "CurrentRatio": "1.68", "SalesQQ": "-8.80", "OperMargin": "-1.11", "RSI14": "21.68", "Volatility": [9.13, 6.02], "Optionable": true, "DebtEq": "1.51", "EPSQQ": "", "ProfitMargin": "-58.34", "RelVolume": "0.43", "PrevClose": "2.36", "Shortable": true, "LTDebtEq": "1.46", "Earnings": "Aug 10 AMC", "Payout": "", "AvgVolume": 450440.0, "Price": "2.38", "Recom": "1.50", "SMA20": "-23.08", "SMA50": "-43.13", "SMA200": "-55.84", "Volume": "192577", "Change": "0.85"}