{"Index": "", "PE": "", "EPSttm": "-0.03", "InsiderOwn": "0.60", "ShsOutstand": 5730000.0, "PerfWeek": "6.51", "LastUpdated": "2021-02-08", "MarketCap": 18610000.0, "ForwardPE": "", "EPSnextY": "", "InsiderTrans": "-91.82", "ShsFloat": 3540000.0, "PerfMonth": "60.29", "Income": -200000.0, "PEG": "", "EPSnextQ": "", "InstOwn": "2.10", "ShortFloat": "1.24", "PerfQuarter": "106.96", "Sales": 1400000.0, "PS": "13.29", "EPSthisY": "94.70", "InstTrans": "27.81", "ShortRatio": "0.01", "PerfHalfY": "155.47", "Booksh": "1.37", "PB": "2.39", "ROA": "-1.80", "TargetPrice": "", "PerfYear": "239.42", "Cashsh": "1.00", "PC": "3.26", "EPSnext5Y": "", "ROE": "-2.20", "FiftyTwoWRange": [0.74, 9.62], "PerfYTD": "74.87", "Dividend": "", "PFCF": "", "EPSpast5Y": "-15.60", "ROI": "-3.80", "FiftyTwoWHigh": "-66.86", "Beta": "0.81", "DividendPercent": "", "QuickRatio": "", "Salespast5Y": "-31.30", "GrossMargin": "", "FiftyTwoWLow": "330.77", "ATR": "0.66", "Employees": "2", "CurrentRatio": "", "SalesQQ": "0.00", "OperMargin": "15.70", "RSI14": "58.00", "Volatility": [14.32, 24.64], "Optionable": false, "DebtEq": "0.03", "EPSQQ": "-119.80", "ProfitMargin": "-12.60", "RelVolume": "0.25", "PrevClose": "3.27", "Shortable": true, "LTDebtEq": "0.03", "Earnings": "", "Payout": "", "AvgVolume": 4139999.9999999995, "Price": "3.19", "Recom": "1.00", "SMA20": "16.23", "SMA50": "47.02", "SMA200": "108.44", "Volume": "348633", "Change": "-2.52"}