{"Sector": "Financial", "Industry": "Exchange Traded Fund", "Country": "USA", "Exchange": "NYSE", "Category": "US Equities - Industry Sector", "AssetType": ["", ""], "Tags": "", "ReturnPercent1Y": "5.76", "ShsOutstand": "\n\n", "PerfWeek": "-2.14", "LastUpdated": "2024-05-26", "Sponsor": "Invesco", "ETFType": "\n\n", "ReturnPercent3Y": "0.65", "TotalHoldings": "23", "PerfMonth": "4.58", "FundFamily": "\n\n", "BondType": "\n\n", "ReturnPercent5Y": "6.68", "AUM": 268350000.00000003, "PerfQuarter": "0.92", "Index": "Dynamic Pharmaceuticals Intellidex Indx", "AverageMaturity": "\n\n", "ReturnPercent10Y": "\n\n", "NAVPercent": "\n\n", "PerfHalfY": "12.63", "IndexWeighting": "\n\n", "CommodityType": "\n\n", "ReturnPercentSI": "\n\n", "NAVsh": "\n\n", "PerfYear": "4.74", "ActivePassive": "\n\n", "QuantType": "\n\n", "FlowsPercent1M": "-1.73", "FiftyTwoWRange": [67.75, 81.2], "PerfYTD": "3.97", "DividendTTM": [0.74, 0.93], "ESGType": "\n\n", "FlowsPercent3M": "-5.00", "FiftyTwoWHigh": "-2.56", "Beta": "0.59", "DividendEx-Date": "Mar 18 2024", "DividendType": "\n\n", "SectorTheme": "\n\n", "FlowsPercentYTD": "-2.63", "FiftyTwoWLow": "16.78", "ATR14": "0.74", "Expense": "0.57", "StructureType": "\n\n", "Region": "\n\n", "FlowsPercent1Y": "\n\n", "RSI14": "47.96", "Volatility": [0.84, 0.89], "OptionShort": true, "GrowthValue": "\n\n", "DevEmerg": "\n\n", "FlowsPercent3Y": "\n\n", "RelVolume": "0.05", "PrevClose": "79.33", "InverseLeveraged": "\n\n", "MarketCap": "\n\n", "Currency": "\n\n", "FlowsPercent5Y": "\n\n", "AvgVolume": 21610.0, "Price": "79.12", "SMA20": "-0.61", "SMA50": "0.65", "SMA200": "4.61", "Trades": "\n\n", "Volume": "1027", "Change": "-0.27"}