{"Index": "", "PE": "", "EPSttm": "", "InsiderOwn": "", "ShsOutstand": "", "PerfWeek": "1.23", "LastUpdated": "2021-02-08", "MarketCap": "", "ForwardPE": "", "EPSnextY": "", "InsiderTrans": "", "ShsFloat": "", "PerfMonth": "0.95", "Income": "", "PEG": "", "EPSnextQ": "", "InstOwn": "", "ShortFloat": "", "PerfQuarter": "5.45", "Sales": "", "PS": "", "EPSthisY": "", "InstTrans": "", "ShortRatio": "", "PerfHalfY": "5.94", "Booksh": "", "PB": "", "ROA": "", "TargetPrice": "", "PerfYear": "", "Cashsh": "", "PC": "", "EPSnext5Y": "", "ROE": "", "FiftyTwoWRange": [25.05, 28.65], "PerfYTD": "1.02", "Dividend": "", "PFCF": "", "EPSpast5Y": "", "ROI": "", "FiftyTwoWHigh": "0.21", "Beta": "", "DividendPercent": "", "QuickRatio": "", "Salespast5Y": "", "GrossMargin": "", "FiftyTwoWLow": "14.61", "ATR": "0.11", "Employees": "", "CurrentRatio": "", "SalesQQ": "", "OperMargin": "", "RSI14": "63.89", "Volatility": [0.28, 0.31], "Optionable": false, "DebtEq": "", "EPSQQ": "", "ProfitMargin": "", "RelVolume": "0.14", "PrevClose": "28.64", "Shortable": true, "LTDebtEq": "", "Earnings": "", "Payout": "", "AvgVolume": 9430.0, "Price": "28.71", "Recom": "", "SMA20": "0.76", "SMA50": "1.21", "SMA200": "4.81", "Volume": "444", "Change": "0.24"}