{"Index": "", "PE": "32.60", "EPSttm": "0.20", "InsiderOwn": "4.10", "ShsOutstand": 49580000.0, "PerfWeek": "14.26", "LastUpdated": "2021-02-09", "MarketCap": 329840000.0, "ForwardPE": "13.57", "EPSnextY": "22.50", "InsiderTrans": "-1.11", "ShsFloat": 35700000.0, "PerfMonth": "11.02", "Income": 10400000.0, "PEG": "1.33", "EPSnextQ": "0.08", "InstOwn": "62.40", "ShortFloat": "1.28", "PerfQuarter": "26.67", "Sales": 830500000.0, "PS": "0.40", "EPSthisY": "-23.20", "InstTrans": "12.35", "ShortRatio": "1.95", "PerfHalfY": "42.40", "Booksh": "2.79", "PB": "2.38", "ROA": "3.50", "TargetPrice": "8.33", "PerfYear": "31.94", "Cashsh": "0.48", "PC": "13.80", "EPSnext5Y": "24.60", "ROE": "7.70", "FiftyTwoWRange": [3.08, 6.65], "PerfYTD": "14.66", "Dividend": "", "PFCF": "8.75", "EPSpast5Y": "15.40", "ROI": "7.50", "FiftyTwoWHigh": "-0.83", "Beta": "1.53", "DividendPercent": "", "QuickRatio": "1.30", "Salespast5Y": "11.20", "GrossMargin": "24.10", "FiftyTwoWLow": "114.12", "ATR": "0.21", "Employees": "603", "CurrentRatio": "1.30", "SalesQQ": "-12.30", "OperMargin": "2.10", "RSI14": "63.70", "Volatility": [3.15, 3.42], "Optionable": true, "DebtEq": "0.25", "EPSQQ": "-3.60", "ProfitMargin": "1.30", "RelVolume": "0.83", "PrevClose": "6.65", "Shortable": true, "LTDebtEq": "0.21", "Earnings": "Feb 09 AMC", "Payout": "0.00", "AvgVolume": 234620.0, "Price": "6.59", "Recom": "2.00", "SMA20": "6.70", "SMA50": "9.26", "SMA200": "31.31", "Volume": "40680", "Change": "-0.83"}