{"Sector": "Financial", "Industry": "Exchange Traded Fund", "Country": "USA", "Exchange": "AMEX", "Category": "US Equities - Factor & Thematic", "AssetType": ["", ""], "Tags": "", "ReturnPercent1Y": "17.65", "ShsOutstand": "\n\n", "PerfWeek": "-0.70", "LastUpdated": "2024-05-26", "Sponsor": "Invesco", "ETFType": "\n\n", "ReturnPercent3Y": "6.49", "TotalHoldings": "81", "PerfMonth": "5.97", "FundFamily": "\n\n", "BondType": "\n\n", "ReturnPercent5Y": "10.21", "AUM": 5190000.0, "PerfQuarter": "5.02", "Index": "S&P 500 Minimum Volatility Index", "AverageMaturity": "\n\n", "ReturnPercent10Y": "\n\n", "NAVPercent": "\n\n", "PerfHalfY": "17.33", "IndexWeighting": "\n\n", "CommodityType": "\n\n", "ReturnPercentSI": "\n\n", "NAVsh": "\n\n", "PerfYear": "14.78", "ActivePassive": "\n\n", "QuantType": "\n\n", "FlowsPercent1M": "-7.42", "FiftyTwoWRange": [35.06, 43.59], "PerfYTD": "10.11", "DividendTTM": [0.91, 2.11], "ESGType": "\n\n", "FlowsPercent3M": "-42.06", "FiftyTwoWHigh": "-0.85", "Beta": "0.85", "DividendEx-Date": "Mar 18 2024", "DividendType": "\n\n", "SectorTheme": "\n\n", "FlowsPercentYTD": "-44.59", "FiftyTwoWLow": "23.28", "ATR14": "0.21", "Expense": "0.10", "StructureType": "\n\n", "Region": "\n\n", "FlowsPercent1Y": "\n\n", "RSI14": "64.16", "Volatility": [0.22, 0.19], "OptionShort": true, "GrowthValue": "\n\n", "DevEmerg": "\n\n", "FlowsPercent3Y": "\n\n", "RelVolume": "0.02", "PrevClose": "43.19", "InverseLeveraged": "\n\n", "MarketCap": "\n\n", "Currency": "\n\n", "FlowsPercent5Y": "\n\n", "AvgVolume": 3180.0, "Price": "43.22", "SMA20": "2.10", "SMA50": "2.56", "SMA200": "9.83", "Trades": "\n\n", "Volume": "71", "Change": "0.07"}