{"Sector": "Financial", "Industry": "Exchange Traded Fund", "Country": "USA", "Exchange": "NYSE", "Category": "Equity - Leveraged / Inverse", "AssetType": ["", ""], "Tags": "", "ReturnPercent1Y": "-49.15", "ShsOutstand": "\n\n", "PerfWeek": "0.47", "LastUpdated": "2024-05-26", "Sponsor": ["", ""], "ETFType": "\n\n", "ReturnPercent3Y": "-29.55", "TotalHoldings": "12", "PerfMonth": "-12.96", "FundFamily": "\n\n", "BondType": "\n\n", "ReturnPercent5Y": "-46.48", "AUM": 569870000.0, "PerfQuarter": "-11.79", "Index": "S&P 500 Index", "AverageMaturity": "\n\n", "ReturnPercent10Y": "\n\n", "NAVPercent": "\n\n", "PerfHalfY": "-35.00", "IndexWeighting": "\n\n", "CommodityType": "\n\n", "ReturnPercentSI": "\n\n", "NAVsh": "\n\n", "PerfYear": "-51.41", "ActivePassive": "\n\n", "QuantType": "\n\n", "FlowsPercent1M": "10.89", "FiftyTwoWRange": [8.41, 18.09], "PerfYTD": "-25.54", "DividendTTM": [0.56, 6.49], "ESGType": "\n\n", "FlowsPercent3M": "8.44", "FiftyTwoWHigh": "-52.46", "Beta": "-2.55", "DividendEx-Date": "Mar 19 2024", "DividendType": "\n\n", "SectorTheme": "\n\n", "FlowsPercentYTD": "9.83", "FiftyTwoWLow": "2.26", "ATR14": "0.25", "Expense": "0.95", "StructureType": "\n\n", "Region": "\n\n", "FlowsPercent1Y": "\n\n", "RSI14": "38.46", "Volatility": [2.39, 2.44], "OptionShort": true, "GrowthValue": "\n\n", "DevEmerg": "\n\n", "FlowsPercent3Y": "\n\n", "RelVolume": "1.15", "PrevClose": "8.76", "InverseLeveraged": "\n\n", "MarketCap": "\n\n", "Currency": "\n\n", "FlowsPercent5Y": "\n\n", "AvgVolume": 28110000.0, "Price": "8.60", "SMA20": "-5.29", "SMA50": "-6.65", "SMA200": "-28.79", "Trades": "\n\n", "Volume": "32271591", "Change": "-1.83"}