{"Index": "", "PE": "", "EPSttm": "", "InsiderOwn": "", "ShsOutstand": "", "PerfWeek": "8.69", "LastUpdated": "2021-02-09", "MarketCap": "", "ForwardPE": "", "EPSnextY": "", "InsiderTrans": "", "ShsFloat": "", "PerfMonth": "", "Income": "", "PEG": "", "EPSnextQ": "", "InstOwn": "", "ShortFloat": "", "PerfQuarter": "", "Sales": "", "PS": "", "EPSthisY": "", "InstTrans": "", "ShortRatio": "", "PerfHalfY": "", "Booksh": "", "PB": "", "ROA": "", "TargetPrice": "", "PerfYear": "", "Cashsh": "", "PC": "", "EPSnext5Y": "", "ROE": "", "FiftyTwoWRange": [24.37, 27.45], "PerfYTD": "10.69", "Dividend": "", "PFCF": "", "EPSpast5Y": "", "ROI": "", "FiftyTwoWHigh": "1.20", "Beta": "", "DividendPercent": "", "QuickRatio": "", "Salespast5Y": "", "GrossMargin": "", "FiftyTwoWLow": "13.99", "ATR": "0.63", "Employees": "", "CurrentRatio": "", "SalesQQ": "", "OperMargin": "", "RSI14": "", "Volatility": [1.5], "Optionable": false, "DebtEq": "", "EPSQQ": "", "ProfitMargin": "", "RelVolume": "0.12", "PrevClose": "27.34", "Shortable": false, "LTDebtEq": "", "Earnings": "", "Payout": "", "AvgVolume": 139610.0, "Price": "27.78", "Recom": "", "SMA20": "6.39", "SMA50": "6.39", "SMA200": "6.39", "Volume": "3502", "Change": "1.61"}