{"Sector": "Technology", "Industry": "Software - Infrastructure", "Country": "USA", "Index": "", "PE": "79.90", "EPSttm": "2.22", "InsiderOwn": "0.40", "ShsOutstand": 44230000.0, "PerfWeek": "10.21", "LastUpdated": "2023-01-13", "MarketCap": 7420000000.0, "ForwardPE": "12.81", "EPSnextY": "3.90", "InsiderTrans": "-7.34", "ShsFloat": 42840000.0, "PerfMonth": "6.94", "Income": 101000000.0, "PEG": "4.03", "EPSnextQ": "3.20", "InstOwn": "", "ShortFloatRatio": "2.89 / 3.41", "PerfQuarter": "31.93", "Sales": 2230000000.0, "PS": "3.33", "EPSthisY": "100.10", "InstTrans": "-0.36", "ShortInterest": 1240000.0, "PerfHalfY": "14.57", "Booksh": "36.88", "PB": "4.81", "ROA": "0.90", "TargetPrice": "185.31", "PerfYear": "13.29", "Cashsh": "18.13", "PC": "9.78", "EPSnext5Y": "19.82", "ROE": "5.60", "FiftyTwoWRange": [125.0, 183.38], "PerfYTD": "8.29", "Dividend": "", "PFCF": "14.52", "EPSpast5Y": "-65.00", "ROI": "5.80", "FiftyTwoWHigh": "-3.42", "Beta": "1.59", "DividendPercent": "", "QuickRatio": "", "Salespast5Y": "12.80", "GrossMargin": "61.60", "FiftyTwoWLow": "41.69", "ATR": "4.95", "Employees": "5600", "CurrentRatio": "", "SalesQQ": "27.60", "OperMargin": "19.00", "RSI14": "66.31", "Volatility": [2.78, 2.92], "Optionable": true, "DebtEq": "1.72", "EPSQQ": "-193.50", "ProfitMargin": "4.50", "RelVolume": "0.57", "PrevClose": "177.22", "Shortable": true, "LTDebtEq": "1.62", "Earnings": "Oct 27 BMO", "Payout": "0.00", "AvgVolume": 362650.0, "Price": "177.11", "Recom": "2.20", "SMA20": "7.61", "SMA50": "8.86", "SMA200": "11.05", "Volume": "102353", "Change": "-0.06"}