{"Index": "-", "P/E": "-", "EPS (ttm)": "-2.00", "Insider Own": "0.20%", "Shs Outstand": "12.64M", "Perf Week": "17.52%", "Market Cap": "215.13M", "Forward P/E": "-", "EPS next Y": "0.70%", "Insider Trans": "-95.94%", "Shs Float": "5.39M", "Perf Month": "14.60%", "Income": "-16.60M", "PEG": "-", "EPS next Q": "-0.43", "Inst Own": "59.80%", "Short Float": "2.13%", "Perf Quarter": "19.11%", "Sales": "39.50M", "P/S": "5.45", "EPS this Y": "-430.00%", "Inst Trans": "-0.31%", "Short Ratio": "4.69", "Perf Half Y": "32.83%", "Book/sh": "3.52", "P/B": "5.24", "ROA": "-20.00%", "Target Price": "24.25", "Perf Year": "-7.70%", "Cash/sh": "5.27", "P/C": "3.50", "EPS next 5Y": "-", "ROE": "-33.50%", "52W Range": "10.29 - 22.99", "Perf YTD": "39.77%", "Dividend": "-", "P/FCF": "-", "EPS past 5Y": "-", "ROI": "-11.40%", "52W High": "-19.75%", "Beta": "-", "Dividend %": "-", "Quick Ratio": "8.80", "Sales past 5Y": "112.80%", "Gross Margin": "57.50%", "52W Low": "79.30%", "ATR": "0.99", "Employees": "82", "Current Ratio": "8.80", "Sales Q/Q": "3.80%", "Oper. Margin": "-38.70%", "RSI (14)": "72.84", "Volatility": "5.73% 6.01%", "Optionable": "No", "Debt/Eq": "0.60", "EPS Q/Q": "76.90%", "Profit Margin": "-42.10%", "Rel Volume": "2.07", "Prev Close": "17.00", "Shortable": "Yes", "LT Debt/Eq": "0.60", "Earnings": "Nov 10 AMC", "Payout": "-", "Avg Volume": "24.51K", "Price": "18.45", "Recom": "1.60", "SMA20": "16.11%", "SMA50": "27.00%", "SMA200": "34.39%", "Volume": "50,800", "Change": "8.53%"}